CHANGELOG.md
README.md
sqlalchemy_model_factory/__init__.py
sqlalchemy_model_factory/base.py
sqlalchemy_model_factory/declarative.py
sqlalchemy_model_factory/py.typed
sqlalchemy_model_factory/pytest.py
sqlalchemy_model_factory/registry.py
sqlalchemy_model_factory/utils.py
sqlalchemy_model_factory-0.4.6.dist-info/entry_points.txt
sqlalchemy_model_factory-0.4.6.dist-info/LICENSE
sqlalchemy_model_factory-0.4.6.dist-info/WHEEL
sqlalchemy_model_factory-0.4.6.dist-info/METADATA
sqlalchemy_model_factory-0.4.6.dist-info/RECORD
