Metadata-Version: 2.1
Name: sqlalchemy-model-factory
Version: 0.4.6
Summary: A library to assist in generating models from a central location.
Home-page: https://github.com/dancardin/sqlalchemy-model-factory
License: Apache-2.0
Keywords: sqlalchemy,model,factory,pytest
Author: Dan Cardin
Author-email: ddcardin@gmail.com
Requires-Python: >=3.6.2,<4
Classifier: License :: OSI Approved :: Apache Software License
Classifier: Programming Language :: Python :: 3
Classifier: Programming Language :: Python :: 3.7
Classifier: Programming Language :: Python :: 3.8
Classifier: Programming Language :: Python :: 3.9
Classifier: Programming Language :: Python :: 3.10
Provides-Extra: pytest
Requires-Dist: pytest (>=1.0); extra == "pytest"
Requires-Dist: sqlalchemy
Requires-Dist: typing_extensions (>=3.10)
Project-URL: Repository, https://github.com/dancardin/sqlalchemy-model-factory
